lib_version/__init__.py
lib_version/version_util.py
lib_version_remla25_team12-0.1.3.dist-info/METADATA
lib_version_remla25_team12-0.1.3.dist-info/WHEEL
lib_version_remla25_team12-0.1.3.dist-info/RECORD
