Metadata-Version: 2.3
Name: lib-version-remla25-team12
Version: 0.1.3
Summary: Library to expose version metadata
Author: Ayush
Requires-Python: >=3.11,<4.0
Classifier: Programming Language :: Python :: 3
Classifier: Programming Language :: Python :: 3.11
Classifier: Programming Language :: Python :: 3.12
Classifier: Programming Language :: Python :: 3.13
